[
  {
    "name": "Изумруд",
    "description": "❇\uFE0F Огромный изумруд невиданной красоты "
  },
  {
    "name": "Жемчужина",
    "description": "⚪"
  },
  {
    "name": "Рубиновый шар",
    "description": "Шар, вырезанный из кроваво-красного рубина"
  },
  {
    "name": "Сапфир",
    "description": "\uD83D\uDC9C"
  },
  {
    "name": "Топаз",
    "description": "Топазы из глазниц черепа"
  },
  {
    "name": "Гранат",
    "description": "Искрящейся красный самоцвет"
  },
  {
    "name": "Бриллиант",
    "description": "\uD83D\uDC8E"
  },
  {
    "name": "Медный ключ",
    "description": "Простой медный ключ \uD83D\uDDDD\uFE0F. Интересно, от чего он?"
  },
  {
    "name": "Ожерелье",
    "description": "Амулет прибаляющий силу \uD83D\uDCAA"
  },
  {
    "name": "Кольчуга карлика",
    "description": "\uD83E\uDDE5 Искусно выкована из первоклассной бронзы"
  },
  {
    "name": "Крюк",
    "description": "\uD83E\uDE9D"
  },
  {
    "name": "Кувшин кислоты",
    "description": "Кувшин с концентрированной кислотой"
  },
  {
    "name": "Латунный колокольчик",
    "description": "Крохотный колокольчик \uD83D\uDD14"
  },
  {
    "name": "Кинжал",
    "description": "\uD83D\uDDE1"
  },
  {
    "name": "Деревянная трубка",
    "description": "Простая полая деревянная трубка "
  },
  {
    "name": "Кольцо Желаний",
    "description": "\uD83D\uDC8D Оно выполнит любое твое желание, но лишь одно!"
  },
  {
    "name": "Крылатый шлем",
    "description": "Шлем изготовлен каким-то умельцем былых времен \uD83D\uDC77"
  },
  {
    "name": "Бронзовый щит",
    "description": "Искусно выкованный бронзовый щит \uD83D\uDEE1\uFE0F"
  },
  {
    "name": "Заметка про мантикора",
    "description": "Заметка гласит «Путник, коль встретится тебе Мантикор, берегись хвоста его. Да убережет тебя твой верный щит от шипов, что наполнят воздух»"
  },
  {
    "name": "Веревка",
    "description": "Веревка из пещеры \uD80C\uDF6F"
  },
  {
    "name": "Cеребряный кубок",
    "description": "\uD83E\uDD5B"
  },
  {
    "name": "Раздвоитель",
    "description": "\uD83E\uDDEA Только одна порция! Напиток сей позволит тебе принять форму любого живого существа, что близ тебя"
  },
  {
    "name": "Костяная обезьянка",
    "description": "Амулет в виде костянной обезьянки"
  },
  {
    "name": "Ходули",
    "description": "Бамбуковые ходули"
  },
  {
    "name": "Зуб лепрекона",
    "description": "Это зуб лепрекон - он приносит удачу \uD83C\uDF40"
  },
  {
    "name": "Кость",
    "description": "Старая засохшая кость \uD83E\uDDB4"
  },
  {
    "name": "Зеркальце",
    "description": ""
  },
  {
    "name": "Молоток",
    "description": ""
  },
  {
    "name": "Медные шипы",
    "description": ""
  }
]